multitool/__init__.py
multitool/__main__.py
multitool/cli.py
multitool/runner.py
multitool/version.py
multitool/assets/Synonyms.json
multitool/assets/Words_Frequency.json
multitool/assets/Words_Length.json
apmultitool-0.1.7.dist-info/LICENSE
apmultitool-0.1.7.dist-info/METADATA
apmultitool-0.1.7.dist-info/WHEEL
apmultitool-0.1.7.dist-info/entry_points.txt
apmultitool-0.1.7.dist-info/top_level.txt
apmultitool-0.1.7.dist-info/RECORD
