Metadata-Version: 2.1
Name: apmultitool
Version: 0.1.7
Summary: CLI Multitool.
Home-page: https://github.com/alexpdev/multitool
Author: alexpdev
Author-email: alexpdev <alexpdev@pm.me>
License: =?utf-8?q?The_MIT_License_=28MIT=29?=
Keywords: CLI
Classifier: Environment :: Console
Classifier: Development Status :: 4 - Beta
Classifier: Operating System :: OS Independent
Classifier: Programming Language :: Python
Classifier: Programming Language :: Python :: 3
Classifier: Programming Language :: Python :: 3.6
Classifier: Programming Language :: Python :: 3.7
Classifier: Programming Language :: Python :: 3.8
Classifier: Programming Language :: Python :: 3.9
Classifier: Programming Language :: Python :: 3.10
Classifier: Programming Language :: Python :: 3 :: Only
Classifier: Intended Audience :: End Users/Desktop
Classifier: Intended Audience :: Developers
Classifier: Topic :: Utilities
Classifier: Topic :: Software Development :: Libraries :: Python Modules
Classifier: License :: OSI Approved :: Apache Software License
Requires-Python: >=3.6
License-File: LICENSE
